README.rst
nbank_registry/__init__.py
nbank_registry/admin.py
nbank_registry/apps.py
nbank_registry/errors.py
nbank_registry/models.py
nbank_registry/resource_download.py
nbank_registry/serializers.py
nbank_registry/tools.py
nbank_registry/urls.py
nbank_registry/views.py
nbank_registry/fixtures/nbank_registry_starter_kit.json
nbank_registry/migrations/0001_initial.py
nbank_registry/migrations/0002_auto_20180511_1141.py
nbank_registry/migrations/0003_auto_20210406_1203.py
nbank_registry/migrations/0004_auto_20210406_1211.py
nbank_registry/migrations/0005_datatype_downloadable.py
nbank_registry/migrations/0006_alter_archive_id_alter_datatype_id_alter_location_id_and_more.py
nbank_registry/migrations/0007_datatype_extension_alter_datatype_content_type.py
nbank_registry/migrations/0008_alter_datatype_extension.py
nbank_registry/migrations/__init__.py
django_neurobank-0.10.12.dist-info/METADATA
django_neurobank-0.10.12.dist-info/WHEEL
django_neurobank-0.10.12.dist-info/licenses/COPYING
django_neurobank-0.10.12.dist-info/RECORD
