Metadata-Version: 2.4
Name: django-neurobank
Version: 0.10.12
Summary: A Django-based registry for the neurobank system
Project-URL: Homepage, https://github.com/melizalab/django-neurobank
Author-email: C Daniel Meliza <dan@meliza.org>
Maintainer-email: C Daniel Meliza <dan@meliza.org>
License: BSD 3-Clause License
License-File: COPYING
Classifier: Development Status :: 4 - Beta
Classifier: Framework :: Django
Classifier: Intended Audience :: Science/Research
Classifier: License :: OSI Approved :: BSD License
Classifier: Programming Language :: Python
Classifier: Programming Language :: Python :: 3.10
Classifier: Programming Language :: Python :: 3.11
Classifier: Programming Language :: Python :: 3.12
Classifier: Topic :: Internet :: WWW/HTTP
Classifier: Topic :: Internet :: WWW/HTTP :: Dynamic Content
Classifier: Topic :: Scientific/Engineering
Requires-Python: >=3.10
Requires-Dist: basehash>=3.0.10
Requires-Dist: django-filter>=22.1
Requires-Dist: django-sendfile2>=0.6.0
Requires-Dist: django>=4.2.17
Requires-Dist: djangorestframework-link-header-pagination
Requires-Dist: djangorestframework>=3.15.2
